{
  "project_info": {
    "project_number": "475200381847",
    "project_id": "campingmate-1425b",
    "storage_bucket": "campingmate-1425b.appspot.com"
  },
  "client": [
    {
      "client_info": {
        "mobilesdk_app_id": "1:475200381847:android:0117f999e1030acbeb5ad2",
        "android_client_info": {
          "package_name": "com.brandon.campingmate"
        }
      },
      "oauth_client": [],
      "api_key": [
        {
          "current_key": "AIzaSyBzGeJRlP7gItTQQxrVGZlrfwIkYxhObaM"
        }
      ],
      "services": {
        "appinvite_service": {
          "other_platform_oauth_client": []
        }
      }
    }
  ],
  "configuration_version": "1"
}